linkshot/__init__.py
linkshot-0.0.1.dist-info/LICENSE
linkshot-0.0.1.dist-info/METADATA
linkshot-0.0.1.dist-info/WHEEL
linkshot-0.0.1.dist-info/top_level.txt
linkshot-0.0.1.dist-info/RECORD
