Metadata-Version: 2.1
Name: linkshot
Version: 0.0.1
Summary: Manage unified linked files
Home-page: https://github.com/manbehindthemadness/linkshot
Author: Manbehindthemadness
Author-email: manbehindthemadness@gmail.com
Classifier: Programming Language :: Python :: 3
Classifier: License :: OSI Approved :: Apache Software License
Classifier: Operating System :: OS Independent
Requires-Python: >=3.5
License-File: LICENSE
